operbot/__init__.py
operbot/modules/__init__.py
operbot/modules/cmd.py
operbot/modules/dbg.py
operbot/modules/err.py
operbot/modules/flt.py
operbot/modules/fnd.py
operbot/modules/irc.py
operbot/modules/log.py
operbot/modules/mbx.py
operbot/modules/mdl.py
operbot/modules/req.py
operbot/modules/rss.py
operbot/modules/sts.py
operbot/modules/tdo.py
operbot/modules/thr.py
operbot/modules/udp.py
operbot/modules/upt.py
operbot/modules/wsd.py
operbot-200.data/data/operbot/operbot.service
operbot-200.data/scripts/operbot
operbot-200.data/scripts/operbotcmd
operbot-200.data/scripts/operbotctl
operbot-200.data/scripts/operbotd
operbot-200.dist-info/METADATA
operbot-200.dist-info/WHEEL
operbot-200.dist-info/top_level.txt
operbot-200.dist-info/RECORD
