Metadata-Version: 2.1
Name: operbot
Version: 200
Summary: operator bot
Home-page: http://github.com/operbot/operbot
Author: Bart Thate
Author-email: thatebhj@gmail.com
License: Public Domain
Platform: UNKNOWN
Classifier: Development Status :: 3 - Alpha
Classifier: License :: Public Domain
Classifier: Operating System :: POSIX :: Linux
Classifier: Programming Language :: Python :: 3 :: Only
Classifier: Intended Audience :: System Administrators
Classifier: Topic :: Communications :: Chat :: Internet Relay Chat
Classifier: Topic :: Software Development :: Libraries :: Python Modules
Requires-Dist: opr
